{
  "id": 1936,
  "title": "Canvas Art Wraps, 1.6\"",
  "description": "<p>Elevate your space or give the gift of stunning art with our premium satin canvas prints. Expertly crafted, each piece is printed to the highest quality on durable 100% polyester canvas, offering a luxurious satin finish that enhances the beauty of your artwork. Your canvas comes pre-stretched around a sturdy 35mm frame, ready to hang with a sleek black backing and an integral hole for easy wall mounting. Available in a range of sizes from 8\" x 12\" to 36\" x 24\", this canvas is perfect for any room or occasion. Whether for your home, office, or as a thoughtful gift, it will surely impress.</p><div>.:Material: Durable 100% polyester</div><br /><div>.:Available in 7 different sizes</div><br /><div>.:Horizontal and vertical options available</div><br /><div>.:Designed for indoor use</div><br /><div>.:Includes black backing with a built-in wall hanger</div>",
  "brand": "Generic brand",
  "model": "",
  "images": [
    "https://images.printify.com/67e534908394b9083c0dd982",
    "https://images.printify.com/67e5356f4966faf0aa0960e2",
    "https://images.printify.com/67e5348f5323877bcf099173"
  ]
}