{
  "timestamp": "2026-05-07 09:54:17 -0400",
  "mode": "NOOP_BELOW_THRESHOLD",
  "execute": false,
  "cdp_port": 9223,
  "memory_soft_pct": 86.0,
  "memory_hard_pct": 92.0,
  "memory_before": 84.9,
  "memory_after": 84.9,
  "cpu_before": 68.0,
  "cpu_after": 68.0,
  "closed_tabs": [],
  "top_processes": [
    {
      "ProcessName": "chrome",
      "Id": 3280,
      "WorkingSetMB": 2434.5,
      "CPU": 7788.03125
    },
    {
      "ProcessName": "Memory Compression",
      "Id": 2944,
      "WorkingSetMB": 625.9,
      "CPU": null
    },
    {
      "ProcessName": "Codex",
      "Id": 27652,
      "WorkingSetMB": 556.3,
      "CPU": 16345.515625
    },
    {
      "ProcessName": "chrome",
      "Id": 9740,
      "WorkingSetMB": 442.4,
      "CPU": 50653.640625
    },
    {
      "ProcessName": "chrome",
      "Id": 21384,
      "WorkingSetMB": 250.8,
      "CPU": 432.796875
    },
    {
      "ProcessName": "explorer",
      "Id": 10468,
      "WorkingSetMB": 221.7,
      "CPU": 3348.484375
    },
    {
      "ProcessName": "Code",
      "Id": 19100,
      "WorkingSetMB": 204,
      "CPU": 1326.265625
    },
    {
      "ProcessName": "MsMpEng",
      "Id": 4564,
      "WorkingSetMB": 190.3,
      "CPU": null
    }
  ],
  "decision": "MEMORY_OK_CONTINUE",
  "reason": "normal work may continue under marketplace risk guards",
  "privacy_rule": "Only closes project automation Edge tabs through CDP 9223. Does not inspect or close Rex's daily Chrome tabs.",
  "rest_rule": "Do not shutdown/restart by default; if pressure stays high after cleanup, write rest-cycle recommendation unless Rex explicitly requests immediate power action."
}